[
  {
    "domain": ".legacy.senate.gov.ph",
    "httpOnly": false,
    "name": "ASPSESSIONIDSATCSCQD",
    "path": "/",
    "sameSite": "Lax",
    "secure": true,
    "value": "LBLNNNDACAACOEDDBBAMKAMP"
  },
  {
    "domain": ".senate.gov.ph",
    "expiry": 1740810081,
    "httpOnly": true,
    "name": "cf_clearance",
    "path": "/",
    "sameSite": "None",
    "secure": true,
    "value": "K55DimMlPhDdBmxLGL9E29hGn8plOtYxr9s9vFpObMw-1709274081-1.0-AZchKsJPce65vzIMflIR/s9dK77ak/in3wpxsU3EQpW8vVJjdFRyU5wePY1tUprK0fUezuTvYBiwu/cQktsrlqI="
  },
  {
    "domain": ".legacy.senate.gov.ph",
    "httpOnly": true,
    "name": "ASP.NET_SessionId",
    "path": "/",
    "sameSite": "Lax",
    "secure": true,
    "value": "xhcaloie0sm2j2uwpx1zh045"
  },
  {
    "domain": "legacy.senate.gov.ph",
    "httpOnly": true,
    "name": "ASP.NET_SessionId",
    "path": "/",
    "sameSite": "Lax",
    "secure": false,
    "value": "h23mtzr53cugx0vl35w3y045"
  }
]