{
  "https://legacy.senate.gov.ph/lis/bill_res.aspx?congress=19&q=SBN-349": {
    "hits": 1,
    "headinfo": {
      "content-length": null,
      "content-type": "text/html; charset=utf-8",
      "content-encoding": "gzip",
      "last-modified": null
    }
  },
  "https://legacy.senate.gov.ph/lis/bill_res.aspx?congress=19&q=SBN-352": {
    "hits": 1,
    "headinfo": {
      "content-length": null,
      "content-type": "text/html; charset=utf-8",
      "content-encoding": "gzip",
      "last-modified": null
    }
  },
  "https://legacy.senate.gov.ph/lis/bill_res.aspx?congress=19&q=SBN-348": {
    "hits": 1,
    "headinfo": {
      "content-length": null,
      "content-type": "text/html; charset=utf-8",
      "content-encoding": "gzip",
      "last-modified": null
    }
  },
  "https://legacy.senate.gov.ph/lis/bill_res.aspx?congress=19&q=SBN-353": {
    "hits": 1,
    "headinfo": {
      "content-length": null,
      "content-type": "text/html; charset=utf-8",
      "content-encoding": "gzip",
      "last-modified": null
    }
  },
  "https://legacy.senate.gov.ph/lis/bill_res.aspx?congress=19&q=SBN-356": {
    "hits": 1,
    "headinfo": {
      "content-length": null,
      "content-type": "text/html; charset=utf-8",
      "content-encoding": "gzip",
      "last-modified": null
    }
  },
  "https://legacy.senate.gov.ph/lis/bill_res.aspx?congress=19&q=SBN-359": {
    "hits": 1,
    "headinfo": {
      "content-length": null,
      "content-type": "text/html; charset=utf-8",
      "content-encoding": "gzip",
      "last-modified": null
    }
  },
  "https://legacy.senate.gov.ph/lis/bill_res.aspx?congress=19&q=SBN-351": {
    "hits": 1,
    "headinfo": {
      "content-length": null,
      "content-type": "text/html; charset=utf-8",
      "content-encoding": "gzip",
      "last-modified": null
    }
  },
  "https://legacy.senate.gov.ph/lis/bill_res.aspx?congress=19&q=SBN-361": {
    "hits": 1,
    "headinfo": {
      "content-length": null,
      "content-type": "text/html; charset=utf-8",
      "content-encoding": "gzip",
      "last-modified": null
    }
  },
  "https://legacy.senate.gov.ph/lis/bill_res.aspx?congress=19&q=SBN-367": {
    "hits": 1,
    "headinfo": {
      "content-length": null,
      "content-type": "text/html; charset=utf-8",
      "content-encoding": "gzip",
      "last-modified": null
    }
  },
  "https://legacy.senate.gov.ph/lis/bill_res.aspx?congress=19&q=SBN-350": {
    "hits": 1,
    "headinfo": {
      "content-length": null,
      "content-type": "text/html; charset=utf-8",
      "content-encoding": "gzip",
      "last-modified": null
    }
  }
}