{
  "https://legacy.senate.gov.ph/DigitalArchives.asp": {
    "hits": 2,
    "headinfo": {
      "content-length": null,
      "content-type": "text/html",
      "content-encoding": "gzip",
      "last-modified": null
    }
  },
  "https://legacy.senate.gov.ph/DigitalArchives.asp/cdn-cgi/apps/head/0Rm8od53jTImAgr2lmH9Zowxsn0.js": {
    "hits": 1,
    "headinfo": {
      "content-length": null,
      "content-type": null,
      "content-encoding": null,
      "last-modified": null
    }
  },
  "https://legacy.senate.gov.ph/DigitalArchives.asp/photo_sample/scripts_web/div.js": {
    "hits": 1,
    "headinfo": {
      "content-length": null,
      "content-type": null,
      "content-encoding": null,
      "last-modified": null
    }
  },
  "https://legacy.senate.gov.ph/DigitalArchives.asp/senators/senlist.asp": {
    "hits": 1,
    "headinfo": {
      "content-length": null,
      "content-type": null,
      "content-encoding": null,
      "last-modified": null
    }
  },
  "https://legacy.senate.gov.ph/about/RULES%20OF%20THE%20SENATE%20MARCH%202023.pdf": {
    "hits": 1,
    "headinfo": {
      "content-length": "541763",
      "content-type": "application/pdf",
      "content-encoding": null,
      "last-modified": "Tue, 06 Jun 2023 07:38:36 GMT"
    }
  },
  "https://legacy.senate.gov.ph/DigitalArchives.asp/photo_sample/scripts_web/print.css": {
    "hits": 1,
    "headinfo": {
      "content-length": null,
      "content-type": null,
      "content-encoding": null,
      "last-modified": null
    }
  },
  "https://legacy.senate.gov.ph/DigitalArchives.asp/senators/roll.asp": {
    "hits": 1,
    "headinfo": {
      "content-length": null,
      "content-type": null,
      "content-encoding": null,
      "last-modified": null
    }
  },
  "https://legacy.senate.gov.ph/DigitalArchives.asp/senators/composition.asp": {
    "hits": 1,
    "headinfo": {
      "content-length": null,
      "content-type": null,
      "content-encoding": null,
      "last-modified": null
    }
  },
  "https://legacy.senate.gov.ph/DigitalArchives.asp/photo_sample/scripts_web/xhtml.css": {
    "hits": 1,
    "headinfo": {
      "content-length": null,
      "content-type": null,
      "content-encoding": null,
      "last-modified": null
    }
  },
  "https://legacy.senate.gov.ph/DigitalArchives.asp/about/history.asp": {
    "hits": 1,
    "headinfo": {
      "content-length": null,
      "content-type": null,
      "content-encoding": null,
      "last-modified": null
    }
  },
  "https://legacy.senate.gov.ph/DigitalArchives.asp/about/symbols%20of%20authority.asp": {
    "hits": 1,
    "headinfo": {
      "content-length": null,
      "content-type": null,
      "content-encoding": null,
      "last-modified": null
    }
  },
  "https://legacy.senate.gov.ph/DigitalArchives.asp/committee/duties.asp": {
    "hits": 1,
    "headinfo": {
      "content-length": null,
      "content-type": null,
      "content-encoding": null,
      "last-modified": null
    }
  },
  "https://legacy.senate.gov.ph/DigitalArchives.asp/senators/sen19th.asp": {
    "hits": 1,
    "headinfo": {
      "content-length": null,
      "content-type": null,
      "content-encoding": null,
      "last-modified": null
    }
  },
  "https://legacy.senate.gov.ph/DigitalArchives.asp/about/legpro.asp": {
    "hits": 1,
    "headinfo": {
      "content-length": null,
      "content-type": null,
      "content-encoding": null,
      "last-modified": null
    }
  },
  "https://legacy.senate.gov.ph/DigitalArchives.asp/notice_ctte.asp": {
    "hits": 1,
    "headinfo": {
      "content-length": null,
      "content-type": null,
      "content-encoding": null,
      "last-modified": null
    }
  },
  "https://legacy.senate.gov.ph/DigitalArchives.asp/committee/oversight_mem19th.pdf": {
    "hits": 1,
    "headinfo": {
      "content-length": null,
      "content-type": null,
      "content-encoding": null,
      "last-modified": null
    }
  },
  "https://legacy.senate.gov.ph/DigitalArchives.asp/committee/schedwk.asp": {
    "hits": 1,
    "headinfo": {
      "content-length": null,
      "content-type": null,
      "content-encoding": null,
      "last-modified": null
    }
  },
  "https://legacy.senate.gov.ph/DigitalArchives.asp/committee/ctte_list19th.pdf": {
    "hits": 1,
    "headinfo": {
      "content-length": null,
      "content-type": null,
      "content-encoding": null,
      "last-modified": null
    }
  },
  "https://legacy.senate.gov.ph/DigitalArchives.asp/secretariat/osec.asp": {
    "hits": 1,
    "headinfo": {
      "content-length": null,
      "content-type": null,
      "content-encoding": null,
      "last-modified": null
    }
  },
  "https://legacy.senate.gov.ph/DigitalArchives.asp/photo_sample/scripts_web/xhtml_body.css": {
    "hits": 1,
    "headinfo": {
      "content-length": null,
      "content-type": null,
      "content-encoding": null,
      "last-modified": null
    }
  },
  "https://legacy.senate.gov.ph/DigitalArchives.asp/secretariat/leg.asp": {
    "hits": 1,
    "headinfo": {
      "content-length": null,
      "content-type": null,
      "content-encoding": null,
      "last-modified": null
    }
  },
  "https://legacy.senate.gov.ph/DigitalArchives.asp/secretariat/admin.asp": {
    "hits": 1,
    "headinfo": {
      "content-length": null,
      "content-type": null,
      "content-encoding": null,
      "last-modified": null
    }
  },
  "https://legacy.senate.gov.ph/DigitalArchives.asp/senators/terms.asp": {
    "hits": 1,
    "headinfo": {
      "content-length": null,
      "content-type": null,
      "content-encoding": null,
      "last-modified": null
    }
  },
  "https://legacy.senate.gov.ph/DigitalArchives.asp/secretariat/officers.asp": {
    "hits": 1,
    "headinfo": {
      "content-length": null,
      "content-type": null,
      "content-encoding": null,
      "last-modified": null
    }
  },
  "https://legacy.senate.gov.ph/DigitalArchives.asp/ctte_quick_notes.asp": {
    "hits": 1,
    "headinfo": {
      "content-length": null,
      "content-type": null,
      "content-encoding": null,
      "last-modified": null
    }
  },
  "https://legacy.senate.gov.ph/DigitalArchives.asp/committee/ctte_mem19th.pdf": {
    "hits": 1,
    "headinfo": {
      "content-length": null,
      "content-type": null,
      "content-encoding": null,
      "last-modified": null
    }
  },
  "https://legacy.senate.gov.ph/DigitalArchives.asp/lis/pdf_sys.aspx?congress=19&type=adopted_res": {
    "hits": 1,
    "headinfo": {
      "content-length": null,
      "content-type": null,
      "content-encoding": null,
      "last-modified": null
    }
  },
  "https://legacy.senate.gov.ph/DigitalArchives.asp/secretariat/extaffairs.asp": {
    "hits": 1,
    "headinfo": {
      "content-length": null,
      "content-type": null,
      "content-encoding": null,
      "last-modified": null
    }
  },
  "https://legacy.senate.gov.ph/DigitalArchives.asp/lis/leg_sys.aspx?congress=19&type=resolution": {
    "hits": 1,
    "headinfo": {
      "content-length": null,
      "content-type": null,
      "content-encoding": null,
      "last-modified": null
    }
  },
  "https://legacy.senate.gov.ph/DigitalArchives.asp/secretariat/osaa.asp": {
    "hits": 1,
    "headinfo": {
      "content-length": null,
      "content-type": null,
      "content-encoding": null,
      "last-modified": null
    }
  },
  "https://legacy.senate.gov.ph/DigitalArchives.asp/committee/adhocctte_list19th.pdf": {
    "hits": 1,
    "headinfo": {
      "content-length": null,
      "content-type": null,
      "content-encoding": null,
      "last-modified": null
    }
  },
  "https://legacy.senate.gov.ph/DigitalArchives.asp/statistical.pdf": {
    "hits": 1,
    "headinfo": {
      "content-length": null,
      "content-type": null,
      "content-encoding": null,
      "last-modified": null
    }
  },
  "https://legacy.senate.gov.ph/DigitalArchives.asp/publications/stsro_publications.asp": {
    "hits": 1,
    "headinfo": {
      "content-length": null,
      "content-type": null,
      "content-encoding": null,
      "last-modified": null
    }
  },
  "https://legacy.senate.gov.ph/DigitalArchives.asp/lis/leg_sys.aspx?congress=19&type=bill": {
    "hits": 1,
    "headinfo": {
      "content-length": null,
      "content-type": null,
      "content-encoding": null,
      "last-modified": null
    }
  },
  "https://legacy.senate.gov.ph/DigitalArchives.asp/lis/leg_sys.aspx?congress=19&type=journal": {
    "hits": 1,
    "headinfo": {
      "content-length": null,
      "content-type": null,
      "content-encoding": null,
      "last-modified": null
    }
  },
  "https://legacy.senate.gov.ph/19th_congress/Treaties/Treaties%20-%2019th%20Congress022724.pdf": {
    "hits": 1,
    "headinfo": {
      "content-length": "719969",
      "content-type": "application/pdf",
      "content-encoding": null,
      "last-modified": "Wed, 28 Feb 2024 02:07:45 GMT"
    }
  },
  "https://legacy.senate.gov.ph/DigitalArchives.asp/lis/leg_sys.aspx?congress=19&type=committee_rpt": {
    "hits": 1,
    "headinfo": {
      "content-length": null,
      "content-type": null,
      "content-encoding": null,
      "last-modified": null
    }
  },
  "https://legacy.senate.gov.ph/DigitalArchives.asp/publications/ils_publications.asp": {
    "hits": 1,
    "headinfo": {
      "content-length": null,
      "content-type": null,
      "content-encoding": null,
      "last-modified": null
    }
  },
  "https://legacy.senate.gov.ph/DigitalArchives.asp/publications/lls_publications.asp": {
    "hits": 1,
    "headinfo": {
      "content-length": null,
      "content-type": null,
      "content-encoding": null,
      "last-modified": null
    }
  },
  "https://legacy.senate.gov.ph/DigitalArchives.asp/lis/pdf_sys.aspx?congress=19&type=republic_act": {
    "hits": 1,
    "headinfo": {
      "content-length": null,
      "content-type": null,
      "content-encoding": null,
      "last-modified": null
    }
  },
  "https://legacy.senate.gov.ph/DigitalArchives.asp/secretariat/mission_vision.asp": {
    "hits": 1,
    "headinfo": {
      "content-length": null,
      "content-type": null,
      "content-encoding": null,
      "last-modified": null
    }
  },
  "https://legacy.senate.gov.ph/DigitalArchives.asp/publications/other_publications.asp": {
    "hits": 1,
    "headinfo": {
      "content-length": null,
      "content-type": null,
      "content-encoding": null,
      "last-modified": null
    }
  },
  "https://legacy.senate.gov.ph/DigitalArchives.asp/publications/sepo_publications.asp": {
    "hits": 1,
    "headinfo": {
      "content-length": null,
      "content-type": null,
      "content-encoding": null,
      "last-modified": null
    }
  },
  "https://legacy.senate.gov.ph/GAD/gad.asp": {
    "hits": 1,
    "headinfo": {
      "content-length": null,
      "content-type": "text/html",
      "content-encoding": "gzip",
      "last-modified": null
    }
  },
  "https://legacy.senate.gov.ph/DigitalArchives.asp/publications/lbrmo_publications.asp": {
    "hits": 1,
    "headinfo": {
      "content-length": null,
      "content-type": null,
      "content-encoding": null,
      "last-modified": null
    }
  },
  "https://legacy.senate.gov.ph/DigitalArchives.asp/publications/lrs_publications.asp": {
    "hits": 1,
    "headinfo": {
      "content-length": null,
      "content-type": null,
      "content-encoding": null,
      "last-modified": null
    }
  },
  "https://legacy.senate.gov.ph/[UPDATED]%20The%20Senators%27%20Directory_10.25.2023.pdf": {
    "hits": 1,
    "headinfo": {
      "content-length": "28736159",
      "content-type": "application/pdf",
      "content-encoding": null,
      "last-modified": "Wed, 25 Oct 2023 03:38:55 GMT"
    }
  },
  "https://legacy.senate.gov.ph/photo_sample/scripts_web/xhtml_body.css": {
    "hits": 1,
    "headinfo": {
      "content-length": null,
      "content-type": "text/css",
      "content-encoding": "gzip",
      "last-modified": "Thu, 12 Nov 2015 03:20:04 GMT"
    }
  },
  "https://legacy.senate.gov.ph/DigitalArchives.asp/job.pdf": {
    "hits": 1,
    "headinfo": {
      "content-length": null,
      "content-type": null,
      "content-encoding": null,
      "last-modified": null
    }
  },
  "https://legacy.senate.gov.ph/images/pdf1.gif": {
    "hits": 1,
    "headinfo": {
      "content-length": "221",
      "content-type": "image/gif",
      "content-encoding": null,
      "last-modified": "Tue, 19 Jun 2007 09:27:30 GMT"
    }
  },
  "https://legacy.senate.gov.ph/DigitalArchives.asp/rss.asp": {
    "hits": 1,
    "headinfo": {
      "content-length": null,
      "content-type": null,
      "content-encoding": null,
      "last-modified": null
    }
  },
  "https://legacy.senate.gov.ph/DigitalArchives.asp/publications/ells_publications.asp": {
    "hits": 1,
    "headinfo": {
      "content-length": null,
      "content-type": null,
      "content-encoding": null,
      "last-modified": null
    }
  },
  "https://legacy.senate.gov.ph/DigitalArchives.asp/sitemap.asp": {
    "hits": 1,
    "headinfo": {
      "content-length": null,
      "content-type": null,
      "content-encoding": null,
      "last-modified": null
    }
  },
  "https://legacy.senate.gov.ph/photo_sample/scripts_web/print.css": {
    "hits": 1,
    "headinfo": {
      "content-length": null,
      "content-type": "text/css",
      "content-encoding": "gzip",
      "last-modified": "Tue, 21 Aug 2007 10:11:50 GMT"
    }
  },
  "https://legacy.senate.gov.ph/photo_sample/scripts_web/div.js": {
    "hits": 1,
    "headinfo": {
      "content-length": null,
      "content-type": "application/x-javascript",
      "content-encoding": "gzip",
      "last-modified": "Wed, 25 Jul 2007 06:40:26 GMT"
    }
  }
}